MANIFEST.in
README.md
setup.py
pylodash/__init__.py
pylodash/arrays.py
pylodash/maths.py
pylodash/number.py
pylodash/string.py
pylodash/utilities.py
pylodash.egg-info/PKG-INFO
pylodash.egg-info/SOURCES.txt
pylodash.egg-info/dependency_links.txt
pylodash.egg-info/not-zip-safe
pylodash.egg-info/requires.txt
pylodash.egg-info/top_level.txt