Metadata-Version: 2.1
Name: pylodash
Version: 0.4.4
Summary: A modern Python utility library delivering modularity, performance & extras.
Home-page: https://gitlab.asoft-python.com/g-tuanluu/python-training
Author: Tuan Luu
Author-email: tuan.luu@asnet.com.vn
License: MIT
Keywords: python lodash utilities pylodash
Platform: UNKNOWN
Classifier: Development Status :: 3 - Alpha
Classifier: License :: OSI Approved :: MIT License
Classifier: Programming Language :: Python :: 3.6
Classifier: Topic :: Text Processing :: Linguistic
